ls_cred_storage/__init__.py
ls_cred_storage/ls_cred_storage.py
ls_cred_storage-0.7.0.dist-info/licenses/LICENSE
ls_cred_storage-0.7.0.dist-info/METADATA
ls_cred_storage-0.7.0.dist-info/WHEEL
ls_cred_storage-0.7.0.dist-info/top_level.txt
ls_cred_storage-0.7.0.dist-info/RECORD
