Metadata-Version: 2.4
Name: ls-cred-storage
Version: 0.7.0
Summary: A package containing storage user credential
Author-email: Assaf Kalinski <assaf@lightsolver.com>
Project-URL: Homepage, https://dev.lightsolver.com
Classifier: Programming Language :: Python :: 3
Classifier: License :: OSI Approved :: Apache Software License
Classifier: Operating System :: OS Independent
Requires-Python: >=3.8
License-File: LICENSE
Requires-Dist: keyring>=23.2.1
Dynamic: license-file
